configs/__init__.py
configs/hxn_pv_config.json
configs/pv_config.json
configs/srx_pv_config-original.json
configs/srx_pv_config.json
configs/tes_pv_config.json
configs/xfm_pv_config.json
configs/xrf_parameter.json
pyxrf/__init__.py
pyxrf/_version.py
pyxrf/api.py
pyxrf/api_dev.py
pyxrf/pyxrf_run.py
pyxrf/core/__init__.py
pyxrf/core/dask_h5py_serializers.py
pyxrf/core/fitting.py
pyxrf/core/map_processing.py
pyxrf/core/quant_analysis.py
pyxrf/core/utils.py
pyxrf/core/xrf_quant_standards.yaml
pyxrf/core/xrf_utils.py
pyxrf/core/yaml_param_files.py
pyxrf/core/tests/__init__.py
pyxrf/core/tests/test_fitting.py
pyxrf/core/tests/test_map_processing.py
pyxrf/core/tests/test_quant_analysis.py
pyxrf/core/tests/test_xrf_utils.py
pyxrf/core/tests/test_yaml_param_files.py
pyxrf/db_config/__init__.py
pyxrf/db_config/hxn_db_config.py
pyxrf/db_config/srx_db_config.py
pyxrf/db_config/tes_db_config.py
pyxrf/db_config/xfm_db_config.py
pyxrf/gui_module/__init__.py
pyxrf/gui_module/central_widget.py
pyxrf/gui_module/dlg_edit_user_peak_parameters.py
pyxrf/gui_module/dlg_export_to_tiff_and_txt.py
pyxrf/gui_module/dlg_find_elements.py
pyxrf/gui_module/dlg_load_mask.py
pyxrf/gui_module/dlg_new_user_peak.py
pyxrf/gui_module/dlg_pileup_peak_parameters.py
pyxrf/gui_module/dlg_plot_escape_peak.py
pyxrf/gui_module/dlg_save_calibration.py
pyxrf/gui_module/dlg_select_quant_standard.py
pyxrf/gui_module/dlg_select_scan.py
pyxrf/gui_module/dlg_view_calib_standard.py
pyxrf/gui_module/dlg_view_metadata.py
pyxrf/gui_module/form_base_widget.py
pyxrf/gui_module/left_panel.py
pyxrf/gui_module/main_window.py
pyxrf/gui_module/right_panel.py
pyxrf/gui_module/tab_wd_fit_maps.py
pyxrf/gui_module/tab_wd_load_data.py
pyxrf/gui_module/tab_wd_model.py
pyxrf/gui_module/tab_wd_plots_fitting_model.py
pyxrf/gui_module/tab_wd_plots_preview.py
pyxrf/gui_module/tab_wd_plots_rgb_maps.py
pyxrf/gui_module/tab_wd_plots_xrf_maps.py
pyxrf/gui_module/useful_widgets.py
pyxrf/gui_module/wd_preview_plot_count.py
pyxrf-1.0.30.dist-info/LICENSE
pyxrf-1.0.30.dist-info/METADATA
pyxrf-1.0.30.dist-info/WHEEL
pyxrf-1.0.30.dist-info/entry_points.txt
pyxrf-1.0.30.dist-info/top_level.txt
pyxrf-1.0.30.dist-info/RECORD
