Metadata-Version: 2.1
Name: pyxrf
Version: 1.0.30
Summary: UNKNOWN
Home-page: https://github.com/NSLS-II/PyXRF
Author: Brookhaven National Laboratory
License: BSD
Platform: UNKNOWN
Classifier: Development Status :: 3 - Alpha
Classifier: License :: OSI Approved :: BSD License
Classifier: Programming Language :: Python :: 3.6
Classifier: Programming Language :: Python :: 3.7
Classifier: Topic :: Software Development :: Libraries
Classifier: Intended Audience :: Science/Research
Requires-Python: >=3.6
License-File: LICENSE
Requires-Dist: setuptools
Requires-Dist: atom
Requires-Dist: dask
Requires-Dist: distributed
Requires-Dist: event-model
Requires-Dist: jsonschema
Requires-Dist: h5py (>=2.9.0)
Requires-Dist: lmfit
Requires-Dist: matplotlib (!=3.3.*)
Requires-Dist: numba
Requires-Dist: numpy (>=1.15)
Requires-Dist: pandas
Requires-Dist: pillow
Requires-Dist: progress
Requires-Dist: pystackreg
Requires-Dist: pyyaml
Requires-Dist: qtpy
Requires-Dist: requests
Requires-Dist: scikit-image
Requires-Dist: scipy
Requires-Dist: tifffile
